{
  "dependencies": {
    "mssql1": {
      "resourceId": "/subscriptions/[parameters('subscriptionId')]/resourceGroups/[parameters('resourceGroupName')]/providers/Microsoft.Sql/servers/bcrmdb/databases/bcrmdb",
      "type": "mssql.azure",
      "connectionId": "bcrmdb.database.windows.net",
      "secretStore": null
    },
    "secrets1": {
      "resourceId": "/subscriptions/[parameters('subscriptionId')]/resourceGroups/[parameters('resourceGroupName')]/providers/Microsoft.KeyVault/vaults/InfolineWorkOfTimeWebPro",
      "type": "secrets.keyVault",
      "connectionId": "VaultUri",
      "secretStore": null
    }
  }
}